{"title":"邓颖超会见日首任驻华大使小川平四郎","authors":[],"dates":[{"year":1986,"month":6,"day":4}],"parts":[{"type":"paragraph","text":"邓颖超会见日首任驻华大使小川平四郎"},{"type":"paragraph","text":"新华社北京6月3日电　全国政协主席邓颖超今天上午在人民大会堂会见日本首任驻中华人民共和国大使、日中协会副会长小川平四郎和夫人。"},{"type":"paragraph","text":"邓颖超对小川平四郎和夫人再次访华表示欢迎，并希望他们经常来中国，多看一些地方。"},{"type":"paragraph","text":"长期研究中国问题的小川平四郎告诉邓颖超，他现在正从事周恩来青年时期活动的研究。"},{"type":"paragraph","text":"邓颖超说，这很好。现在关于周恩来的传记出得很多，但有些不够准确。她希望有一本准确记载周恩来历史活动的书。"},{"type":"paragraph","text":"外交学会会长韩念龙会见时在座。（附图片）"},{"type":"paragraph","text":"6月3日，全国政协主席邓颖超在北京人民大会堂会见日本首任驻中国大使、日中协会副会长小川平四郎和夫人。"},{"type":"paragraph","text":"新华社记者　马俊田摄"}],"comments":[],"comment_pivots":[],"description":"","page_start":4,"page_end":4}