{"title":"颂斯大林","authors":[],"dates":[{"year":1949,"month":12,"day":25}],"parts":[{"type":"paragraph","text":"颂斯大林"},{"type":"paragraph","text":"苏联民歌  靖华译"},{"type":"paragraph","text":"斯大林呵！"},{"type":"paragraph","text":"我们珍存着"},{"type":"paragraph","text":"你的战斗的红旗，"},{"type":"paragraph","text":"我们爱护着"},{"type":"paragraph","text":"你的英明的金言"},{"type":"paragraph","text":"就象生命，就象麋鹿似的。"},{"type":"paragraph","text":"斯大林！"},{"type":"paragraph","text":"你就同海上的太阳一楼。"},{"type":"paragraph","text":"你伟大，"},{"type":"paragraph","text":"亲切，"},{"type":"paragraph","text":"你的英明的事业"},{"type":"paragraph","text":"与有力的智慧"},{"type":"paragraph","text":"强大无比。"},{"type":"paragraph","text":"花岗岩似的斯大林呵，"},{"type":"paragraph","text":"我们珍贵你，"},{"type":"paragraph","text":"爱戴你，"},{"type":"paragraph","text":"在大洋上，"},{"type":"paragraph","text":"在苔藓地带里，"},{"type":"paragraph","text":"我们歌颂你。"},{"type":"paragraph","text":"我们的土地上"},{"type":"paragraph","text":"有两个太阳，"},{"type":"paragraph","text":"一个我们怀着高傲的心情"},{"type":"paragraph","text":"叫他作——"},{"type":"paragraph","text":"“斯大林！”"},{"type":"paragraph","text":"（这是苏联沙阿姆民歌的一段，译出祝斯大林七十寿。）"}],"comments":[],"comment_pivots":[],"description":"","page_start":5,"page_end":5}