{"title":"二次海南行","authors":["朱光"],"dates":[{"year":1960,"month":10,"day":26}],"parts":[{"type":"paragraph","text":"二次海南行（三首）"},{"type":"paragraph","text":"朱光"},{"type":"paragraph","text":"问海"},{"type":"paragraph","text":"重来南海问沧波，"},{"type":"paragraph","text":"肆虐风姨几度过，"},{"type":"paragraph","text":"浪静无垠如晓镜，"},{"type":"paragraph","text":"红霞起处有渔歌。"},{"type":"paragraph","text":"椰林散"},{"type":"paragraph","text":"步滨海椰林欲搏天，"},{"type":"paragraph","text":"迎风凤翼舞翩翩，"},{"type":"paragraph","text":"村童放牧煨椰熟，"},{"type":"paragraph","text":"浪涌潮来月正圆。"},{"type":"paragraph","text":"游林场"},{"type":"paragraph","text":"林场百里郁苍苍，"},{"type":"paragraph","text":"处处山腰拓垦忙，"},{"type":"paragraph","text":"铁马奔驰芟野棘，"},{"type":"paragraph","text":"高歌公社好家乡。"}],"comments":[],"comment_pivots":[],"description":"","page_start":8,"page_end":8}