{"title":"鄂伦春的金翅膀","authors":["傅纯生"],"dates":[{"year":1982,"month":6,"day":29}],"parts":[{"type":"paragraph","text":"鄂伦春的金翅膀"},{"type":"paragraph","text":"傅纯生"},{"type":"paragraph","text":"兴安岭高呵，沾河水长，"},{"type":"paragraph","text":"鄂伦春颠簸在马背上。"},{"type":"paragraph","text":"帐篷挡不住风和雨，"},{"type":"paragraph","text":"皮袍难敌数九的霜。"},{"type":"paragraph","text":"天当被哟，地当床，"},{"type":"paragraph","text":"遍数着星月盼天亮。"},{"type":"paragraph","text":"兴安岭高呵，沾河水长，"},{"type":"paragraph","text":"鄂伦春盼来了好春光。"},{"type":"paragraph","text":"木垒的小房开了扇扇窗，"},{"type":"paragraph","text":"吊锅里犴肉扑鼻香。"},{"type":"paragraph","text":"捧起杯呵，庆定居，"},{"type":"paragraph","text":"口弦琴悠扬歌声响。"},{"type":"paragraph","text":"兴安岭高呵，沾河水长，"},{"type":"paragraph","text":"鄂伦春插上了金翅膀。"},{"type":"paragraph","text":"飞机播云又布雨，"},{"type":"paragraph","text":"收割机麦海破金浪。"},{"type":"paragraph","text":"庄稼上场哟，人上马，"},{"type":"paragraph","text":"重踏兴安狩猎场……"}],"comments":[],"comment_pivots":[],"description":"","page_start":8,"page_end":8}