{"title":"莫洛托夫今日六十寿辰  中共中央、政务院周总理、中苏友协刘会长均致电热烈祝贺","authors":[],"dates":[{"year":1950,"month":3,"day":9}],"parts":[{"type":"paragraph","text":"莫洛托夫今日六十寿辰"},{"type":"paragraph","text":"中共中央、政务院周总理、中苏友协刘会长均致电热烈祝贺"},{"type":"paragraph","text":"【新华社北京八日电】今年三月九日为莫洛托夫六十寿辰，中共中央致电莫洛托夫和联共（布）中央祝贺，电文如下：亲爱的莫洛托夫同志和苏联共产党（布）中央委员会全体同志们："},{"type":"paragraph","text":"欣逢莫洛托夫同志六十寿辰，谨致热烈的祝贺。"},{"type":"paragraph","text":"中国共产党中央委员会"},{"type":"paragraph","text":"三月八日"},{"type":"paragraph","text":"【新华社北京八日电】政务院周恩来总理致电祝贺苏联部长会议副主席莫洛托夫六十寿辰，电文如下：苏联部长会议副主席莫洛托夫先生阁下："},{"type":"paragraph","text":"在阁下六十寿辰之际，谨祝健康和长寿。"},{"type":"paragraph","text":"中华人民共和国中央人民政府政务院总理  周恩来"},{"type":"paragraph","text":"三月八日"},{"type":"paragraph","text":"【新华社北京八日电】中苏友好协会总会刘少奇会长，电贺苏联部长会议副主席莫洛托夫六十寿辰。电文如下：苏联部长会议副主席莫洛托夫先生："},{"type":"paragraph","text":"欣逢您的六十寿辰，谨向您致挚诚热烈的祝贺。"},{"type":"paragraph","text":"中苏友好协会总会会长  刘少奇"},{"type":"paragraph","text":"一九五○年三月八日"}],"comments":[],"comment_pivots":[],"description":"","page_start":1,"page_end":1}