{"title":"祖国捧起的红星","authors":["方竟成"],"dates":[{"year":1992,"month":5,"day":15}],"parts":[{"type":"paragraph","text":"祖国捧起的红星"},{"type":"paragraph","text":"方竟成"},{"type":"paragraph","text":"是穷苦人的揭竿"},{"type":"paragraph","text":"是一八四○点燃铁炮的后代"},{"type":"paragraph","text":"组成了震撼岁月的呼唤"},{"type":"paragraph","text":"戴红星的队伍"},{"type":"paragraph","text":"从这里经过"},{"type":"paragraph","text":"与敌人决战"},{"type":"paragraph","text":"一颗红叶般"},{"type":"paragraph","text":"燃烧的星星"},{"type":"paragraph","text":"掉在了岩石的夹缝"},{"type":"paragraph","text":"——死亡与诞生之间"},{"type":"paragraph","text":"一束红草"},{"type":"paragraph","text":"长成了一篇"},{"type":"paragraph","text":"血染的故事"},{"type":"paragraph","text":"盈耳松涛激荡着"},{"type":"paragraph","text":"挺直脊梁的英勇和"},{"type":"paragraph","text":"燃烧到最后一滴血的悲壮"},{"type":"paragraph","text":"夜空的星星"},{"type":"paragraph","text":"成为敬慕的眼睛"},{"type":"paragraph","text":"望着你的闪烁"},{"type":"paragraph","text":"用祖国的手掌"},{"type":"paragraph","text":"才能捧起你的"},{"type":"paragraph","text":"真正分量"},{"type":"paragraph","text":"当仔细地寻找"},{"type":"paragraph","text":"寻找到山谷中留存的回音"},{"type":"paragraph","text":"东方霞光"},{"type":"paragraph","text":"正撒出一捧"},{"type":"paragraph","text":"红珊瑚般的花瓣"}],"comments":[],"comment_pivots":[],"description":"","page_start":8,"page_end":8}