{"title":"图片","authors":["陈梦涛","杨富学","王箭","谢朝阳"],"dates":[{"year":2003,"month":12,"day":16}],"parts":[{"type":"paragraph","text":"近年来，民航不断加大投入，引进先进的设施、技术，提高行业的现代化程度。"},{"type":"paragraph","text":"图①：多家中外合资飞机维修企业的建立，促进民航维修业的发展。"},{"type":"paragraph","text":"陈梦涛摄"},{"type":"paragraph","text":"图②：集采购、储运、加注为一体的航油销售网络覆盖全国。图为飞机加油场面。　　　　　　　　杨富学摄"},{"type":"paragraph","text":"图③：1980年以来，中国民航购买、租赁飞机近700架，并进口大量配套设施，推动了各航空公司机队的现代化建设。图为飞行模拟训练机。　　　　　　　　　　王箭摄"},{"type":"paragraph","text":"图④：通用航空发展迅速，全国已有通用航空企业40余家。图为通用航空作业。　　　　    谢朝阳摄"}],"comments":[],"comment_pivots":[],"description":"","page_start":15,"page_end":15}