{"title":"李伯曼大使举行酒会  庆祝德意志民主共和国建国二十八周年","authors":[],"dates":[{"year":1977,"month":10,"day":8}],"parts":[{"type":"paragraph","text":"李伯曼大使举行酒会"},{"type":"paragraph","text":"庆祝德意志民主共和国建国二十八周年"},{"type":"paragraph","text":"新华社一九七七年十月七日讯　为庆祝德意志民主共和国建国二十八周年，德意志民主共和国驻中国大使李伯曼和夫人今天下午举行酒会。"},{"type":"paragraph","text":"应邀出席酒会的有第一机械工业部部长周子健，外交部副部长余湛，外贸部副部长郑义山，北京市革委会副秘书长王笑一，对外友协副会长林林。"},{"type":"paragraph","text":"各国驻中国的外交使节也应邀出席。"}],"comments":[],"comment_pivots":[],"description":"","page_start":4,"page_end":4}