{"title":"调粮容易卸粮难　苦了运输部门","authors":["陈维禧"],"dates":[{"year":1988,"month":4,"day":30}],"parts":[{"type":"paragraph","text":"调粮容易卸粮难"},{"type":"paragraph","text":"苦了运输部门"},{"type":"paragraph","text":"四月三日，在乌鲁木齐市八一面粉厂大门前的马路上，等待卸粮的汽车有一百六十四辆，而且大多数是拖挂车。这些车队排了足足有一公里半长。他们是执行国家调粮任务，冒风顶雪一路风尘三四天，从伊犁地区运来的小麦，到这里却卸不下去。有的已经等了八九天了。司机怕粮食丢失，白天黑夜都得守在车旁。"},{"type":"paragraph","text":"八一面粉厂也有苦衷，他们生产的红粮（七五粉）堆满了仓库，调不出去，两个车间已被迫停产，无法大量收粮。这事虽早已反映给上级有关部门了，但迟迟得不到解决。"},{"type":"paragraph","text":"新疆经济导报　陈维禧（附图片）"}],"comments":[],"comment_pivots":[],"description":"","page_start":5,"page_end":5}