{"title":"布达拉宫即景","authors":["陈惟清"],"dates":[{"year":1994,"month":9,"day":29}],"parts":[{"type":"paragraph","text":"布达拉宫即景"},{"type":"paragraph","text":"陈惟清"},{"type":"paragraph","text":"一"},{"type":"paragraph","text":"红日照山巅，金光入眼帘。"},{"type":"paragraph","text":"群山抱粉屋，白雪映红檐。"},{"type":"paragraph","text":"云雾梁边绕，曲径接蓝天。"},{"type":"paragraph","text":"伟哉藏胞艺，留芳千万年。"},{"type":"paragraph","text":"二"},{"type":"paragraph","text":"行行歇歇步高楼，"},{"type":"paragraph","text":"喘喘吁吁不罢休，"},{"type":"paragraph","text":"心急屡嫌脚步缓，"},{"type":"paragraph","text":"眼勤频叹艺无俦。"},{"type":"paragraph","text":"雕梁画栋层层锦，"},{"type":"paragraph","text":"翡翠珊瑚件件优，"},{"type":"paragraph","text":"步到顶楼明晃晃，"},{"type":"paragraph","text":"金光影里似云游。"}],"comments":[],"comment_pivots":[],"description":"","page_start":5,"page_end":5}