{"title":"印尼羽毛球公开赛我选手大部过关","authors":[],"dates":[{"year":1988,"month":7,"day":23}],"parts":[{"type":"paragraph","text":"印尼羽毛球公开赛我选手大部过关"},{"type":"paragraph","text":"据新华社北京7月22日电  据外电报道，20日开始的印度尼西亚羽毛球公开赛男女单打迄今已进入了第三轮。"},{"type":"paragraph","text":"参赛的中国选手除男子新秀吴文凯在第三轮中被一号种子、印尼的苏吉亚托淘汰外，其余的均进入了八分之一决赛。"},{"type":"paragraph","text":"中国选手在第三轮比赛中，女子李玲蔚胜吉英儿（南朝鲜）2∶1，黄华胜李英淑（南朝鲜）2∶0，唐九红胜保基（印尼）2∶0，孙小青胜埃利奥特（英格兰）2∶0；男子赵剑华胜库尔尼亚贾亚（印尼）2∶0，熊国宝胜苏普里扬托（印尼）2∶0。"}],"comments":[],"comment_pivots":[],"description":"","page_start":3,"page_end":3}