{"title":"诗三首","authors":["沈鹏"],"dates":[{"year":1996,"month":11,"day":16}],"parts":[{"type":"paragraph","text":"诗三首"},{"type":"paragraph","text":"沈鹏"},{"type":"paragraph","text":"《曹禺全集》即将出版有作"},{"type":"paragraph","text":"彤云摧压郁雷奔，"},{"type":"paragraph","text":"遥夜沉沉叩帝阍。"},{"type":"paragraph","text":"一读魂灵一震颤，"},{"type":"paragraph","text":"年年再造北京人。"},{"type":"paragraph","text":"商务印书馆百年"},{"type":"paragraph","text":"草剑守成披棘榛，"},{"type":"paragraph","text":"中西邃密百科陈。"},{"type":"paragraph","text":"一灯花结经风雨，"},{"type":"paragraph","text":"百岁文星主树人。"},{"type":"paragraph","text":"题白石老人画雏鸡菊花签"},{"type":"paragraph","text":"霜素何年暗转黄？"},{"type":"paragraph","text":"雏鸡汝亦历沧桑。"},{"type":"paragraph","text":"五归五出求新变，"},{"type":"paragraph","text":"衰岁童真星斗塘。"}],"comments":[],"comment_pivots":[],"description":"","page_start":7,"page_end":7}