{"title":"望江南","authors":["熊明修"],"dates":[{"year":1995,"month":5,"day":18}],"parts":[{"type":"paragraph","text":"望江南"},{"type":"paragraph","text":"熊明修"},{"type":"paragraph","text":"从江南雨中传来的蛙歌"},{"type":"paragraph","text":"总爱容留新到的燕子"},{"type":"paragraph","text":"裁剪"},{"type":"paragraph","text":"映山红的光芒"},{"type":"paragraph","text":"从映山红的根部"},{"type":"paragraph","text":"辉映到江南草的枝枝蔓蔓"},{"type":"paragraph","text":"江南的父老乡亲"},{"type":"paragraph","text":"在生命和雨水的遥望中"},{"type":"paragraph","text":"驮起犁铧敞开吆喝"},{"type":"paragraph","text":"深一脚浅一脚地"},{"type":"paragraph","text":"走进墒情"},{"type":"paragraph","text":"哦江南"},{"type":"paragraph","text":"我听见春光和春雨"},{"type":"paragraph","text":"均匀落地的声音"},{"type":"paragraph","text":"我看见撒种人的眼窝里"},{"type":"paragraph","text":"关不住的是春色"},{"type":"paragraph","text":"储藏着的是秋天"},{"type":"paragraph","text":"（附图片）"},{"type":"paragraph","text":"小溪（中国画）孔紫"}],"comments":[],"comment_pivots":[],"description":"","page_start":10,"page_end":10}