{"title":"鲁迅博物馆收到一件新礼物","authors":[],"dates":[{"year":1962,"month":7,"day":27}],"parts":[{"type":"paragraph","text":"鲁迅博物馆收到一件新礼物"},{"type":"paragraph","text":"上海中国画院的老画家钱瘦铁，最近将他自己创作的一幅描写鲁迅家乡风光的《鲁迅故乡揽胜》图赠送给北京鲁迅博物馆。"},{"type":"paragraph","text":"这幅长四百七十二厘米、宽四十一厘米的画卷，概括地描绘了鲁迅家乡纵横二百多里范围内的秀丽风光，其中有鲁迅诞生地及其故居百草园，鲁迅童年读书处三味书屋，鲁迅童年看社戏的地方，以及鲁迅童年朋友闰土的家乡等地。"},{"type":"paragraph","text":"钱瘦铁是位六十五岁高龄的画家。这幅画卷是他在1957年访问鲁迅故乡后创作的。"},{"type":"paragraph","text":"（据新华社讯）"}],"comments":[],"comment_pivots":[],"description":"","page_start":2,"page_end":2}