{"title":"周总理同北京二千多中小学教师联欢","authors":[],"dates":[{"year":1956,"month":6,"day":10}],"parts":[{"type":"paragraph","text":"周总理同北京二千多中小学教师联欢"},{"type":"paragraph","text":"新华社9日讯　周恩来总理今晚在青年团中央礼堂和北京二千多个中、小学教师在一起度过了愉快的周末。"},{"type":"paragraph","text":"在布满彩色电灯的庭院里，教师们举行着联欢晚会。"},{"type":"paragraph","text":"周总理来到这里的时候，被教师们热情地簇拥着，他在跳舞厅和教师们见了面。"},{"type":"paragraph","text":"中国著名教育家吴玉章、徐特立、陈伯达、董纯才、林砺儒，今晚也和教师们一起欣赏了师生们演出的许多文艺节目。"}],"comments":[],"comment_pivots":[],"description":"","page_start":1,"page_end":1}