{"title":"红荷","authors":["田歌"],"dates":[{"year":1986,"month":10,"day":30}],"parts":[{"type":"paragraph","text":"红荷"},{"type":"paragraph","text":"田歌"},{"type":"paragraph","text":"红荷是水乡的青春"},{"type":"paragraph","text":"把村庄都照得嫩绿嫩绿的"},{"type":"paragraph","text":"红荷是水乡的思想"},{"type":"paragraph","text":"把日子都照得火红火红的"},{"type":"paragraph","text":"这深情的鱼水情呵"},{"type":"paragraph","text":"这青春永驻的热情呵"},{"type":"paragraph","text":"就在干瘪的日子也未凋谢过"},{"type":"paragraph","text":"那红艳艳的火红捂也捂不住"},{"type":"paragraph","text":"季节一到就开花"},{"type":"paragraph","text":"那热情把四周渲染得生气勃勃"},{"type":"paragraph","text":"金鲤又跳波了"},{"type":"paragraph","text":"菱角又结满塘了"},{"type":"paragraph","text":"蛙声又叫千里稻香了"},{"type":"paragraph","text":"风光旖旎而漫天碧透"},{"type":"paragraph","text":"红荷是水乡的青春"},{"type":"paragraph","text":"青春自然要抽出荷箭绽出红花"},{"type":"paragraph","text":"红荷是水乡的思想"},{"type":"paragraph","text":"思想自然要结出香喷喷的收获"}],"comments":[],"comment_pivots":[],"description":"","page_start":8,"page_end":8}