{"title":"迷信品何以吃香？","authors":["裴艺元"],"dates":[{"year":1986,"month":11,"day":2}],"parts":[{"type":"paragraph","text":"迷信品何以吃香？"},{"type":"paragraph","text":"裴艺元"},{"type":"paragraph","text":"江苏省盐城市的部分农村集市上，近来封建迷信品屡有出售，笔者在一个花圈店里看到，纸糊的洋房、别墅、轿车、彩电、冰箱、沙发以及纸做的皮袄、西装、蝙蝠衫、牛仔裤、汗衫、背心等应有尽有，有些农民不惜几十元、上百元买回去付之一炬。"},{"type":"paragraph","text":"封建迷信品进入市场，对迷信活动的传播和泛滥起着推波助澜的作用。此风为什么如此昌盛？据调查，有些从事市场管理的干部认为现在放开了，可以撒手不问了。有些同志虽然想管，但分不清封建迷信活动与宗教信仰的界限。此外，现在一些电影、电视作品里，烧香磕头的镜头比比皆是，也助长了迷信风。"}],"comments":[],"comment_pivots":[],"description":"","page_start":2,"page_end":2}