{"title":"大运会准备工作基本就绪","authors":["颜世贵"],"dates":[{"year":2001,"month":7,"day":26}],"parts":[{"type":"paragraph","text":"大运会准备工作基本就绪"},{"type":"paragraph","text":"本报北京7月25日讯记者颜世贵报道：经过两年多紧张的筹备，第二十一届世界大学生运动会的各项准备工作目前已基本就绪。"},{"type":"paragraph","text":"据大运会组委会秘书长孙康林今天介绍，到目前为止，报名参加本届大运会的国家和地区已达152个，报名人数达到6625人，还邀请了一些国际奥委会委员，规模有望超过历届大运会。"},{"type":"paragraph","text":"他说，目前大运会各项工作已经进入了后期整合阶段。7月份以来，竞赛、技术保障、安全保卫、交通保障等各工作系统陆续进入演练和试运行，各系统工作程序的组合和相关技术保障系统完成了联试联调，建立起了各工作系统的运行、控制、管理机制。"},{"type":"paragraph","text":"大运会52个比赛、训练场馆已做好了接待准备。占地11.2公顷的大运村将于8月10日封村，8月15日开村。"}],"comments":[],"comment_pivots":[],"description":"","page_start":8,"page_end":8}