{"title":"通勤日记一则","authors":["永臣"],"dates":[{"year":1980,"month":7,"day":4}],"parts":[{"type":"paragraph","text":"通勤日记一则"},{"type":"paragraph","text":"永臣"},{"type":"paragraph","text":"人多车少，照例还是拥挤。"},{"type":"paragraph","text":"行车中，突然一个急刹车，全车人猛地向前拥去。一个中年工人身不由己地撞到一位颇时髦的女郎身上，并在她的锃亮的皮鞋上踩了一脚。立刻，那女郎骂不绝口：“……缺德、流氓、损贼……”污秽之言不堪入耳。那工人只是连声道歉。"},{"type":"paragraph","text":"一个小伙子实在看不惯，对那女郎说：“同志，请自爱一点。知道不？这是公共汽车，不是结婚坐花轿，美滋滋的一个人。缺乏道德修养！”"},{"type":"paragraph","text":"话音未落，全车乘客哄然大笑。"}],"comments":[],"comment_pivots":[],"description":"","page_start":8,"page_end":8}