{"title":"沁园春——党的六十九周年纪念志感","authors":["熊复"],"dates":[{"year":1990,"month":7,"day":11}],"parts":[{"type":"paragraph","text":"沁园春"},{"type":"paragraph","text":"——党的六十九周年纪念志感"},{"type":"paragraph","text":"熊复"},{"type":"paragraph","text":"大好神州，"},{"type":"paragraph","text":"光昌流丽，"},{"type":"paragraph","text":"气象万千。"},{"type":"paragraph","text":"念山河再造，"},{"type":"paragraph","text":"已然非易；"},{"type":"paragraph","text":"中华复兴，"},{"type":"paragraph","text":"尤属维艰。"},{"type":"paragraph","text":"雄立东方，"},{"type":"paragraph","text":"量天裁地，"},{"type":"paragraph","text":"四化期成有指南。"},{"type":"paragraph","text":"看今日，"},{"type":"paragraph","text":"正舜尧英发，"},{"type":"paragraph","text":"破浪而前。"},{"type":"paragraph","text":"当年星火燎原，"},{"type":"paragraph","text":"征鞍上指麾定九寰。"},{"type":"paragraph","text":"记烈贤作楷，"},{"type":"paragraph","text":"捐躯恐后，"},{"type":"paragraph","text":"明灯引路，"},{"type":"paragraph","text":"奋勇争先。"},{"type":"paragraph","text":"雨暴风狂，"},{"type":"paragraph","text":"无何所畏，"},{"type":"paragraph","text":"慷慨悲歌唱凯旋。"},{"type":"paragraph","text":"乐观在，"},{"type":"paragraph","text":"有理真义正，"},{"type":"paragraph","text":"血碧心丹。"},{"type":"paragraph","text":"一九九○年七月"}],"comments":[],"comment_pivots":[],"description":"","page_start":5,"page_end":5}