{"title":"京华之春——“两会”感题","authors":["梁上泉"],"dates":[{"year":1991,"month":4,"day":3}],"parts":[{"type":"paragraph","text":"京华之春"},{"type":"paragraph","text":"——“两会”感题"},{"type":"paragraph","text":"人大代表  梁上泉"},{"type":"paragraph","text":"春在不知不觉中到"},{"type":"paragraph","text":"鸟在不知不觉中来"},{"type":"paragraph","text":"树在不知不觉中绿"},{"type":"paragraph","text":"花在不知不觉中开"},{"type":"paragraph","text":"只有人最为清醒"},{"type":"paragraph","text":"已规划到五年十载"},{"type":"paragraph","text":"心潮推涌着春潮"},{"type":"paragraph","text":"早激起叶浪花海"},{"type":"paragraph","text":"都说京华之春最短"},{"type":"paragraph","text":"刚一到位呵夏又赶来"},{"type":"paragraph","text":"可别放过大好辰光"},{"type":"paragraph","text":"快把祖国的新装剪裁＊"}],"comments":[],"comment_pivots":[],"description":"","page_start":2,"page_end":2}