{"title":"南斯拉夫议会代表团名单","authors":[],"dates":[{"year":1957,"month":9,"day":17}],"parts":[{"type":"paragraph","text":"南斯拉夫议会代表团名单"},{"type":"paragraph","text":"新华社16日讯　南斯拉夫联邦人民共和国联邦国民议会代表团名单如下："},{"type":"paragraph","text":"团长："},{"type":"paragraph","text":"彼得·斯坦鲍利奇"},{"type":"paragraph","text":"南斯拉夫联邦国民议会主席，南斯拉夫共产主义者联盟中央执行委员会委员，塞尔维亚共产主义者联盟中央委员。"},{"type":"paragraph","text":"团员："},{"type":"paragraph","text":"菲利普·拜科维奇"},{"type":"paragraph","text":"南斯拉夫联邦国民议会联邦院议员，联邦执行委员会委员。门的内哥罗人民共和国执行委员会主席，门的内哥罗人民共和国共产主义者联盟中央委员。"},{"type":"paragraph","text":"马里扬·布雷策利"},{"type":"paragraph","text":"南斯拉夫联邦国民议会联邦院议员，联邦商品流通国务秘书处秘书长，斯洛文尼亚共产主义者联盟中央委员。"},{"type":"paragraph","text":"斯特凡·多罗尼斯基"},{"type":"paragraph","text":"南斯拉夫联邦国民议会联邦院议员，南斯拉夫共产主义者联盟中央委员，南斯拉夫劳动人民社会主义联盟联邦院委员，伏伊伏丁那自治省国民议会主席。"},{"type":"paragraph","text":"约西普·察齐"},{"type":"paragraph","text":"联邦国民议会生产者院经济组织委员会主席，南斯拉夫共产主义者联盟中央委员，克罗地亚人民共和国国民议会生产者院主席，克罗地亚人民共和国工会主席。"},{"type":"paragraph","text":"格鲁约·诺瓦科维奇"},{"type":"paragraph","text":"联邦国民议会联邦院议员，南斯拉夫共产主义者联盟中央检察委员会委员，波斯尼亚—黑塞哥维那人民共和国执行委员会委员。"},{"type":"paragraph","text":"弗兰约·加日"},{"type":"paragraph","text":"联邦国民议会联邦院议员，克罗地亚人民共和国执行委员会委员。"},{"type":"paragraph","text":"米莱娃·普兰诺耶维奇（女）"},{"type":"paragraph","text":"联邦国民议会联邦院议员，人民解放战争战士协会中央委员，塞尔维亚劳动人民社会主义联盟中央委员。"},{"type":"paragraph","text":"克尔斯托·马尔科夫斯基"},{"type":"paragraph","text":"联邦国民议会联邦院议员，马其顿共产主义者联盟中央执行委员会委员。"},{"type":"paragraph","text":"锡南·哈萨尼"},{"type":"paragraph","text":"联邦国民议会联邦院议员，戈索伏—密托希亚自治区执行委员会委员，塞尔维亚共产主义者联盟戈索伏—密托希亚自治区委员会委员。"}],"comments":[],"comment_pivots":[],"description":"","page_start":4,"page_end":4}