{"title":"瑞士选手摘取世界田径大赛首枚金牌  中国王秀婷刷新女子三千米亚洲纪录","authors":["史克栋"],"dates":[{"year":1987,"month":8,"day":31}],"parts":[{"type":"paragraph","text":"瑞士选手摘取世界田径大赛首枚金牌"},{"type":"paragraph","text":"中国王秀婷刷新女子三千米亚洲纪录"},{"type":"paragraph","text":"本报罗马8月29日电　记者史克栋报道：在第二届世界田径锦标赛第一天的比赛中，中国选手王秀婷虽然未能进入女子3000米的决赛，但在该项预赛中她以8分50秒68的成绩一下把我国选手陈青梅保持的9分0秒90的亚洲纪录缩短了10秒多。"},{"type":"paragraph","text":"本届锦标赛的第一枚金牌被瑞士选手韦尔纳夺得，他以22米23摘取男子铅球赛桂冠。世界纪录保持者、意大利的安德烈以21米88名列第二。"},{"type":"paragraph","text":"男子10000米金牌由肯尼亚选手基普科奇夺得，成绩是27分38秒63，打破上届锦标赛的纪录。中国运动员张国伟名列第14。"},{"type":"paragraph","text":"在女子马拉松比赛中，身高只有1米57的葡萄牙选手莫塔以2小时25分17秒获得冠军。"},{"type":"paragraph","text":"本报罗马8月30日电　记者史克栋报道：中国运动员于厚润、侯雪梅今天在第二届世界田径锦标赛女子铁饼及格赛中，成绩分别为56米70和58米26，均未达到62米50的及格标准，因而被淘汰。"}],"comments":[],"comment_pivots":[],"description":"","page_start":3,"page_end":3}