{"title":"英科学家认为西北欧洪灾与全球变暖有关","authors":["谷利源"],"dates":[{"year":1995,"month":2,"day":5}],"parts":[{"type":"paragraph","text":"英科学家认为"},{"type":"paragraph","text":"西北欧洪灾与全球变暖有关"},{"type":"paragraph","text":"据新华社伦敦２月２日电（记者谷利源）英国科学家认为，西北欧最近遭受的严重洪灾是全球变暖所致。"},{"type":"paragraph","text":"英国东昂吉利亚大学气候研究所的迈克·休尔姆博士昨天在英国气候变化大会上说，这场使许多人丧生和数千人撤离家园的洪灾横扫荷兰、德国和法国，其直接原因是暴雨和积雪提早溶化，而这种现象可能是北纬地区全球变暖所致。"},{"type":"paragraph","text":"他认为，各国政府应当采取一致行动来减少温室气体的排放，否则在５０年之内世界气温将会上升到破坏性的程度。"},{"type":"paragraph","text":"自上世纪中叶以来，全球气温上升了０．５摄氏度，但科学家们对此是否由于温室效应所引起还有不同看法。科学家们担心的是，全球气温稍有变化就会对气候模式产生激烈的影响，导致海平面上升。"},{"type":"paragraph","text":"但是，另一些科学家对北欧洪灾与全球变暖之说有不同看法，认为与全球变暖无关。"}],"comments":[],"comment_pivots":[],"description":"","page_start":7,"page_end":7}