{"title":"“欧洲之父”魂移先贤祠  莫内理想召唤欧洲人","authors":["沈孝泉"],"dates":[{"year":1988,"month":11,"day":12}],"parts":[{"type":"paragraph","text":"“欧洲之父”魂移先贤祠  莫内理想召唤欧洲人"},{"type":"paragraph","text":"据新华社巴黎11月9日电　（记者沈孝泉）被誉为“欧洲之父”的法国著名政治家让·莫内的骨灰今天被隆重地移葬在巴黎的先贤祠内，以表彰他为促进欧洲建设所做的不朽贡献。"},{"type":"paragraph","text":"法国总统密特朗在移葬仪式上致辞时，把莫内这位致力于欧洲建设的先驱称颂为“欧洲第一公民”。他认为欧洲建设应该包括以下内容：共同货币、社会和文化的欧洲、面向第三世界和欧洲防务。"},{"type":"paragraph","text":"他呼吁欧洲各国人民把欧洲建设这一伟大事业继续下去。"},{"type":"paragraph","text":"今天是莫内诞生一百周年。早在40年代，莫内就提出了欧洲国家走向联合的主张。"},{"type":"paragraph","text":"莫内于1979年3月16日逝世。"},{"type":"paragraph","text":"逝世前，他撰写的回忆录中再一次为加速欧洲建设而呼吁。"},{"type":"paragraph","text":"莫内写道：“除了联合之外，欧洲各国人民没有其他任何前途。”"},{"type":"paragraph","text":"坐落在塞纳河畔的先贤祠是安葬法国最杰出的人物的地方。伏尔泰、卢梭、雨果、左拉等人均安葬在这里。"}],"comments":[],"comment_pivots":[],"description":"","page_start":7,"page_end":7}