{"title":"起舞晓霜劲倍添","authors":["许士杰"],"dates":[{"year":1989,"month":3,"day":21}],"parts":[{"type":"paragraph","text":"起舞晓霜劲倍添"},{"type":"paragraph","text":"一"},{"type":"paragraph","text":"荡开闷气亮蓝天，虽有浮云却了然。"},{"type":"paragraph","text":"冷眼静观潮涨退，平心细察水回旋。"},{"type":"paragraph","text":"无根污水曾流淌，有翅谣言也翩跹。"},{"type":"paragraph","text":"春雨霏霏润万物，清风习习扫尘烟。"},{"type":"paragraph","text":"二"},{"type":"paragraph","text":"万利难求皆得兼，利多害少怎能嫌。"},{"type":"paragraph","text":"应从总体评成败，未可个人论苦甜。"},{"type":"paragraph","text":"综合宽严安自治，公开监督政当廉。"},{"type":"paragraph","text":"布新除旧宜安定，起舞晓霜劲倍添。"},{"type":"paragraph","text":"一九八九年三月二十日"},{"type":"paragraph","text":"于北京"}],"comments":[],"comment_pivots":[],"description":"","page_start":3,"page_end":3}