{"title":"李泽厚当选巴黎国际哲学院院士","authors":["华新"],"dates":[{"year":1989,"month":3,"day":9}],"parts":[{"type":"paragraph","text":"李泽厚当选巴黎国际哲学院院士"},{"type":"paragraph","text":"本报北京３月８日讯  著名学者、中国社会科学院哲学所研究员李泽厚日前复信巴黎国际哲学院，同意当选为该院正式成员（即院士）。"},{"type":"paragraph","text":"这是继冯友兰在３０年代当选后，进入巴黎国际哲学院的第二名中国学者。"},{"type":"paragraph","text":"巴黎国际哲学院成立于１９３７年，宗旨是“使世界哲学界的优秀代表人物”“加强学术观点的交流”，设有院士席位１１５名。现有的１１０名院士均为世界著名的哲学家。李泽厚是在１９８８年８月英国布莱顿会议上当选为院士的。"},{"type":"paragraph","text":"（华新）"}],"comments":[],"comment_pivots":[],"description":"","page_start":2,"page_end":2}