{"title":"安哥拉民族解放军击落葡萄牙飞机","authors":[],"dates":[{"year":1964,"month":11,"day":23}],"parts":[{"type":"paragraph","text":"安哥拉民族解放军击落葡萄牙飞机"},{"type":"paragraph","text":"新华社阿尔及尔电　安哥拉民族主义者十六日在这里发表安哥拉前几周的战报说：在罗安达东南的丹博斯地方击落一架葡萄牙T—6型飞机，两名机上人员被击毙。"},{"type":"paragraph","text":"民族解放军的巡逻队在安哥拉中部的木桑德打死六名葡萄牙士兵。"},{"type":"paragraph","text":"在安哥拉东北部卢安戈河附近，民族解放军的巡逻队袭击了葡萄牙军新近建立的一个营地，打死敌人七名，缴获五台发报机。"},{"type":"paragraph","text":"（附图片）"},{"type":"paragraph","text":"安哥拉民族解放军的战士们整队出操。　新华社发"}],"comments":[],"comment_pivots":[],"description":"","page_start":4,"page_end":4}