{"title":"南斯拉夫外长发表谈话　排除外国军队进入南的可能性","authors":["严正"],"dates":[{"year":1991,"month":8,"day":24}],"parts":[{"type":"paragraph","text":"南斯拉夫外长发表谈话"},{"type":"paragraph","text":"排除外国军队进入南的可能性"},{"type":"paragraph","text":"本报贝尔格莱德８月２２日电  记者严正报道：南斯拉夫外长隆查尔今天坚定地排除外国军队进入南斯拉夫以及在南领土之外解决南问题的可能性。"},{"type":"paragraph","text":"隆查尔是在贝尔格莱德举行的外交部例行记者招待会上作上述表示的。"},{"type":"paragraph","text":"隆查尔指出，外国，特别是大国和欧共体可以对南国内的某些进程产生影响。但是，“不要幻想别人能替我们解决问题而又不损害我们的利益”。"}],"comments":[],"comment_pivots":[],"description":"","page_start":6,"page_end":6}