{"title":"文明古国希腊行","authors":["范承补"],"dates":[{"year":1986,"month":4,"day":6}],"parts":[{"type":"paragraph","text":"文明古国希腊行"},{"type":"paragraph","text":"范承补"},{"type":"paragraph","text":"雅典古城堡（一）"},{"type":"paragraph","text":"高堡殿堂异秦塚，圆柱石像精雕功。"},{"type":"paragraph","text":"同是纪元前文化，欧亚人类智无穷。"},{"type":"paragraph","text":"巴特农神庙（二）"},{"type":"paragraph","text":"石构楼群白玉冈，古城何处不堂皇？"},{"type":"paragraph","text":"壮伟更在城台上，玲珑神庙破天荒。"},{"type":"paragraph","text":"宙斯庙遗址（三）"},{"type":"paragraph","text":"降祸赐福神中神，威力无比主浮沉。"},{"type":"paragraph","text":"如此宙斯何处也？擎天石柱今犹存。"},{"type":"paragraph","text":"古剧场观戏（四）"},{"type":"paragraph","text":"两千年前建剧场，二十世纪尚辉煌。"},{"type":"paragraph","text":"万众入座观旧戏，景物古色又古香。"},{"type":"paragraph","text":"访奥林匹亚（五）"},{"type":"paragraph","text":"智慧勇敢孰能全？军民体育列为先。"},{"type":"paragraph","text":"奥林匹亚遗迹在，距今二千七百年。"},{"type":"paragraph","text":"马拉松怀古（六）"},{"type":"paragraph","text":"侵希未计路险巇，波斯自恃有万骑。"},{"type":"paragraph","text":"盖因马拉松一战，弱胜强负见高低。"},{"type":"paragraph","text":"注释："},{"type":"paragraph","text":"（一）这座古城堡是古希腊雅典城邦的一座卫城，初建于公元前八世纪。"},{"type":"paragraph","text":"（二）巴特农神庙历来被喻为古代建筑史上的“杰作”。巴特农神即希腊神话中的处女神，指雅典的守护神雅典娜。"},{"type":"paragraph","text":"（三）宙斯是希腊神话中的主神，威力无边，能降祸赐福，并掌管雷电云雨。"},{"type":"paragraph","text":"（四）这座建于公元前的露天剧场有一万八千个石构座位。剧场呈扇形，据说音响效果特好。"},{"type":"paragraph","text":"（五）奥林匹亚是古希腊体育竞技活动中心，也是人类体育运动的一个发源地。"},{"type":"paragraph","text":"（六）马拉松位于雅典城东约四十二公里处，公元前490年，希腊军队在此击败了入侵的波斯骑兵。（附图片）"},{"type":"paragraph","text":"题图：在奥林匹亚燃点奥林匹克火炬"}],"comments":[],"comment_pivots":[],"description":"","page_start":7,"page_end":7}