{"title":"西藏中药材获得好收成","authors":[],"dates":[{"year":1966,"month":1,"day":7}],"parts":[{"type":"paragraph","text":"西藏中药材获得好收成"},{"type":"paragraph","text":"据新华社讯　西藏中药材去年获得民主改革以来最好的收成。目前商业部门收购的各种中药材已有三十多万斤，超过预定收购计划的百分之四十，是历年来收购最多的一年。"},{"type":"paragraph","text":"名贵药材麝香、丹皮、虫草去年都超额完成了国家收购的计划。其中麝香共收购二万三千多两，丹皮比一九六四年增加一倍半。农牧民出售的药材中，还有鹿茸、豹骨、熊胆等。"},{"type":"paragraph","text":"西藏的药材资源异常丰富，其中用途大、经济价值高的药用植物就有四十六种，而且蕴藏量大。"},{"type":"paragraph","text":"为使翻身农牧民增加收入，民主改革后人民政府采取各种措施来扶持农牧民采集药材，并且提高了药材的收购价格。现在，药材生产已经成为农牧民发展多种经营、增加收入的一个重要途径。从一九六○年到现在，翻身农牧民以出售药材得到的收入已达一千一百多万元。"}],"comments":[],"comment_pivots":[],"description":"","page_start":2,"page_end":2}