{"title":"徐闻汽运公司知错即改","authors":["邓世贵"],"dates":[{"year":1995,"month":4,"day":24}],"parts":[{"type":"paragraph","text":"徐闻汽运公司知错即改"},{"type":"paragraph","text":"你报二月六日读者来信版刊登我写的题为《客车搞“接力”苦煞坐车人》的来信后，广东徐闻县汽车运输总站立即对司乘人员进行轮训，整改营运风气，重新修订有关管理措施。该站党总支副书记张庆任等一行四人，还专程到海口向当事人道歉。"},{"type":"paragraph","text":"我二月二十一日再次从湛江返回海口时，又从雷州市的英利镇坐上了广东徐闻县汽车总站客运车队的客车，司机和售票员的态度和蔼可亲，与先前大不一样。如售票员在乘客上车时先问明到什么地方，然后逐一介绍行驶路线、站名等；过去停车站等客时间过长的现象也没有了。"},{"type":"paragraph","text":"（广州军区海南企业局政治部　邓世贵）"}],"comments":[],"comment_pivots":[],"description":"","page_start":9,"page_end":9}