{"title":"要闻快报","authors":[],"dates":[{"year":1960,"month":11,"day":14}],"parts":[{"type":"paragraph","text":"要闻快报"},{"type":"paragraph","text":"广西大规模秋收"},{"type":"paragraph","text":"广西双季晚稻和秋杂粮作物相继黄熟，一个以抢速度、保质量为特点的大规模秋收运动已经开始。"},{"type":"paragraph","text":"为了保证秋收速度，各人民公社的生产队都集中劳力进行抢收。许多地方还积极推广使用快速收割器，工效比使用镰刀提高一倍到两倍。"},{"type":"paragraph","text":"安徽收双季晚稻"},{"type":"paragraph","text":"安徽各地双季晚稻已普遍收割。为了把今年最后一季粮食作物收细收净，都采取黄一片、收一片、先黄先收的措施，加快了收获进度，提高了质量。到8日止，全省双季晚稻已收割了70％以上。"},{"type":"paragraph","text":"江西抢种油菜"},{"type":"paragraph","text":"江西各地到7日止已完成油菜计划种植面积58％。播种较早的已破土出苗，育苗移栽的已一片葱绿。结合播种，各地都建立了丰产田、丰产片，并且广泛培育“油菜王”。油菜丰产田、丰产片一般都占到总面积20％到30％。"},{"type":"paragraph","text":"云南抢种“宝瓜”——洋丝瓜"},{"type":"paragraph","text":"云南各地人民公社正乘大好季节，普遍种植“宝瓜”——洋丝瓜，许多地区已经形成群众性突击活动。"},{"type":"paragraph","text":"洋丝瓜是一种适应性很强的多年生植物。云南全省绝大部分地区都能种植；房前屋后、大树根旁、墙脚下都是它最好的生长地方，管理也很简单，一直可生长十多年，而且产量一年比一年高。洋丝瓜既是好蔬菜，又是好饲料。因此人们叫它“宝瓜”。"},{"type":"paragraph","text":"为新社员修制大批农具"},{"type":"paragraph","text":"福建省晋江专区修补制造了大批农具，供应给新回到农业第一线的社员们。永春县拨了二百立方米的木材和一百吨生铁，专供各个农具厂生产农具。惠安县上游公社农械厂集中90％的工人大修大补旧农具，使全社每个新老社员每人都有两三件。"}],"comments":[],"comment_pivots":[],"description":"","page_start":2,"page_end":2}