{"title":"在我们生活里——有朋自远方来","authors":[],"dates":[{"year":1990,"month":9,"day":6}],"parts":[{"type":"paragraph","text":"在我们生活里——"},{"type":"paragraph","text":"有朋自远方来"},{"type":"paragraph","text":"自古以来，我国一直被世人誉为礼义之邦，我国人民与各国人民友好交往的历史源远流长。"},{"type":"paragraph","text":"今天，改革开放，国门敞开，五洲的宾客，八方的朋友，更是纷纷来我国旅游、参观、访问、考察、学习……他们的足迹遍及城市、乡村。他们带来了异国的人情风俗，也带来了各国人民的真情一片。他们的到来，给我们生活增添了新的色彩。"},{"type":"paragraph","text":"各国人民的心是相通的——珍惜友谊，维护团结，希望进步，热爱和平。"},{"type":"paragraph","text":"让我们手拉手、肩并肩，为创建一个美好的世界，共同奋进。"},{"type":"paragraph","text":"有朋自远方来，不亦乐乎！"},{"type":"paragraph","text":"·编者·"},{"type":"paragraph","text":"（附图片）"},{"type":"paragraph","text":"↑　外籍专家戴碧铎曾先后5次到河南新乡刘庄访问。老乡们说：这位老戴，是我们“编外村民”。"},{"type":"paragraph","text":"李轲摄"},{"type":"paragraph","text":"呵！我们登上了长城！"},{"type":"paragraph","text":"王文泉摄"},{"type":"paragraph","text":"→　穿上龙袍，戴上凤冠，别有一番情趣。"},{"type":"paragraph","text":"张曙光摄"},{"type":"paragraph","text":"出色的小使者　王文扬摄学做儿童广播操"},{"type":"paragraph","text":"王文波摄"},{"type":"paragraph","text":"↑　这位德国友人与车上的残疾妇女只是偶遇相识，人类互助互爱之情，使他们结为朋友。"},{"type":"paragraph","text":"本报记者  王景仁摄"},{"type":"paragraph","text":"↓买双虎头鞋带回去，是中国之行的最好纪念。"},{"type":"paragraph","text":"吴学华摄"}],"comments":[],"comment_pivots":[],"description":"","page_start":8,"page_end":8}