{"title":"拉那烈呼吁民柬回到柬社会中来","authors":[],"dates":[{"year":1994,"month":2,"day":15}],"parts":[{"type":"paragraph","text":"拉那烈呼吁民柬"},{"type":"paragraph","text":"回到柬社会中来"},{"type":"paragraph","text":"新华社金边２月１３日电柬埔寨王国政府第一首相兼皇家军队联合总司令诺罗敦·拉那烈，今晚在国家电视台宣读了他向民主柬埔寨方面官兵发表的呼吁书。他呼吁民柬官兵及其控制区的人民尽快回到柬埔寨社会中来。"},{"type":"paragraph","text":"拉那烈说，目前，皇家军队已经控制了民柬在暹粒、奥多棉吉、磅同、柏威夏和班迭棉吉地区的基地，特别是安龙文基地。他重申，王国政府遵循诺罗敦·西哈努克国王的民族团结的政治路线，本着民族和解、民族团结和为柬人民谋求和平与安宁的精神，从临时民族政府到现在，为实现民族团结与和解作出了不懈的努力。"},{"type":"paragraph","text":"拉那烈呼吁民柬官兵及其控制区的人民尽快回到柬社会中来。他说，王国政府会表示热烈的欢迎。"}],"comments":[],"comment_pivots":[],"description":"","page_start":6,"page_end":6}