{"title":"苏宁未发表的军事学术论文手稿","authors":[],"dates":[{"year":1991,"month":6,"day":12}],"parts":[{"type":"paragraph","text":"苏宁未发表的军事学术论文手稿"},{"type":"paragraph","text":"１．关于用对策论组织对抗演习的建议"},{"type":"paragraph","text":"２．关于现行《射击教程》的几点补充意见"},{"type":"paragraph","text":"３．试论现代地面战争中的制火权"},{"type":"paragraph","text":"４．野战阵地防御战斗步炮携同几个问题的探讨"},{"type":"paragraph","text":"５．用对策论研究选择排支撑点兵力兵器配置最优方案"},{"type":"paragraph","text":"６．用对策论研究选择野战防御最佳方案——对纵深机动防御战术的初步探讨"},{"type":"paragraph","text":"７．编制装备必须适应现代战争的需要"},{"type":"paragraph","text":"８．根据敌军防御特点研究改革护送射击的方法"},{"type":"paragraph","text":"９．当敌开进展开时我炮兵火力运用的几点建议"},{"type":"paragraph","text":"１０．现代条件下提高炮兵火力反应能力问题初探"},{"type":"paragraph","text":"１１．首先压制敌炮兵是提高炮兵生存力的关键"},{"type":"paragraph","text":"１２．提高对支撑点射击效果的方法"},{"type":"paragraph","text":"１３．创造性地计划火力，确保步坦顺利突破"},{"type":"paragraph","text":"１４．对“纵深机动防御战术”的初步探讨"},{"type":"paragraph","text":"１５．对炮兵火力密度（猛烈程度）的定量分析"},{"type":"paragraph","text":"１６．用坦克冲击成功率计算炮火准备中对支撑点的压制指标"},{"type":"paragraph","text":"１７．验差射求取火炮初速偏差量的新方法"},{"type":"paragraph","text":"１８．统计学在军事领域的应用"},{"type":"paragraph","text":"１９．系统工程在军事领域的应用"},{"type":"paragraph","text":"２０．也谈如何计算反坦克单位"},{"type":"paragraph","text":"２１．用“战斗树”方法计算反坦克武器命效"},{"type":"paragraph","text":"２２．用“随机格斗理论”计算反坦克兵器的战斗效能"},{"type":"paragraph","text":"２３．试论炮火“软杀伤”——对炮火袭击中的非物质战斗力损耗的初步探讨"},{"type":"paragraph","text":"２４．纵深机动防御体系初探"},{"type":"paragraph","text":"２５．根据敌防御特点研究改进护送射击的方法"},{"type":"paragraph","text":"２６．浅谈战争领域中的张与弛"},{"type":"paragraph","text":"２７．对突破口压制射击时毁伤指标小数的计算程序"},{"type":"paragraph","text":"２８．用坦克冲击成功率计算炮火准备毁伤指标"},{"type":"paragraph","text":"２９．用坦克冲击成功率计算对突破口炮火准备的压制指标"},{"type":"paragraph","text":"３０．对支撑点射击几种火力分配方法的效果分析"},{"type":"paragraph","text":"３１．按目标群区分火力对支撑点射击"},{"type":"paragraph","text":"３２．以炮兵营为基本火力单位的几点看法"},{"type":"paragraph","text":"３３．指挥员应重视学习系统分析的方法"},{"type":"paragraph","text":"３４．提高对支撑点射击效果的方法"},{"type":"paragraph","text":"３５．对炮兵火力“无形打击作用”的数学思考——兼论即时战斗力方程"},{"type":"paragraph","text":"３６．陆军师野战阵地防御战斗对抗博弈模型（计算机辅助作战模拟）"},{"type":"paragraph","text":"３７．对点面结合火力分配方法的一点质疑"},{"type":"paragraph","text":"３８．试论坦克紧随我炮弹炸点冲击的可行性——再谈坦克分队炮火安全界的计算"},{"type":"paragraph","text":"３９．对现行安全界规定及计算方法的改进意见"},{"type":"paragraph","text":"４０．对纵深机动防御战术的初步探讨"},{"type":"paragraph","text":"４１．团炮兵群在炮火准备中的压制能力问题初探"},{"type":"paragraph","text":"４２．验差射求取火炮初速偏差量的简便方法"},{"type":"paragraph","text":"４３．坚持三个面向，搞好军事训练改革"},{"type":"paragraph","text":"４４．陆军师野战阵地防御战斗对抗博弈模型"},{"type":"paragraph","text":"４５．运用对策论和数字计算的方法组织和评定演习"},{"type":"paragraph","text":"４６．试论火力反准备"}],"comments":[],"comment_pivots":[],"description":"","page_start":3,"page_end":3}