{"title":"乌干达总统总理分别会见宴请谷牧一行","authors":[],"dates":[{"year":1987,"month":4,"day":28}],"parts":[{"type":"paragraph","text":"乌干达总统总理分别会见宴请谷牧一行"},{"type":"paragraph","text":"据新华社坎帕拉4月26日电　乌干达总统穆塞韦尼今天下午在恩德培国家宫接见了由国务委员谷牧率领的中国政府代表团。"},{"type":"paragraph","text":"他赞扬了乌干达和中国之间存在的关系，并高度评价中国对乌干达的援助。"},{"type":"paragraph","text":"谷牧对中、乌两国友好合作关系的发展表示赞赏。他说，中国政府准备进一步发展这种关系，并准备探讨两国可能合作的新领域。"},{"type":"paragraph","text":"据新华社坎帕拉4月24日电　乌干达总理基塞卡今天在这里的国际会议中心举行宴会，欢迎由国务委员谷牧率领的中国政府代表团。"},{"type":"paragraph","text":"据新华社坎帕拉4月25日电　中国政府和乌干达政府今天在这里签署一项经济技术合作协议。"},{"type":"paragraph","text":"对外经济贸易部副部长吕学俭和乌干达外交部长易卜拉欣·莫基比分别代表本国政府在协议上签了字。"},{"type":"paragraph","text":"根据协议，中国将从今年7月1日起，五年内向乌干达提供2130万美元的无息贷款，用于建造一座体育场和两国政府确定的其他项目。"}],"comments":[],"comment_pivots":[],"description":"","page_start":6,"page_end":6}