{"title":"恩科莫被任命津巴布韦副总统","authors":[],"dates":[{"year":1988,"month":1,"day":3}],"parts":[{"type":"paragraph","text":"恩科莫被任命津巴布韦副总统"},{"type":"paragraph","text":"新华社内罗毕1月2日电  据今天在这里收到的报道，津巴布韦非洲人民联盟领导人乔舒阿·恩科莫已被任命为津巴布韦的两名副总统之一。"},{"type":"paragraph","text":"提名恩科莫为副总统是在去年12月22日津巴布韦非洲民族联盟和津巴布韦非洲人民联盟签订统一协议后作出的。"},{"type":"paragraph","text":"恩科莫和前副总理西蒙·穆增达均已被任命为副总统，地位相等。"},{"type":"paragraph","text":"恩科莫曾经和新总统罗伯特·穆加贝一起在津巴布韦1980年取得独立前领导游击队反对白人统治。"},{"type":"paragraph","text":"任命恩科莫为副总统表明，自从1982年以来恩科莫同穆加贝领导的津巴布韦非洲民族联盟的不和已经结束。"}],"comments":[],"comment_pivots":[],"description":"","page_start":6,"page_end":6}