{"title":"三峡二题","authors":["高洪波"],"dates":[{"year":2002,"month":12,"day":22}],"parts":[{"type":"paragraph","text":"三峡二题"},{"type":"paragraph","text":"高洪波"},{"type":"paragraph","text":"致奉节"},{"type":"paragraph","text":"一座挂在悬崖边的城市"},{"type":"paragraph","text":"一座停在陡坡上的城市"},{"type":"paragraph","text":"一座浮在水面上的城市"},{"type":"paragraph","text":"一座飘在云端里的城市"},{"type":"paragraph","text":"哦，奉节，我的奉节"},{"type":"paragraph","text":"一座让末路英雄刘备大悲哀的城市"},{"type":"paragraph","text":"一座令智慧人物孔明太无奈的城市"},{"type":"paragraph","text":"一座使诗仙李白欣喜若狂的城市"},{"type":"paragraph","text":"一座叫诗圣杜甫慷慨高歌的城市"},{"type":"paragraph","text":"曾一度飘散着清丽竹枝词的城市"},{"type":"paragraph","text":"曾一度回荡着沉郁川江号子的城市"},{"type":"paragraph","text":"一度这座城诗与歌交织"},{"type":"paragraph","text":"一度这座城血与火相迸（注一）"},{"type":"paragraph","text":"哦，奉节，我的奉节"},{"type":"paragraph","text":"你这古老而又过于年轻的城市"},{"type":"paragraph","text":"现实又充满憧憬的城市"},{"type":"paragraph","text":"你这被推土机悍然推倒的城市"},{"type":"paragraph","text":"又被打桩机猛烈夯实的城市"},{"type":"paragraph","text":"一座二千年历史沉入水下的城市"},{"type":"paragraph","text":"一座五年里突兀崛起的城市"},{"type":"paragraph","text":"哦，奉节，我的奉节"},{"type":"paragraph","text":"一座让有形的三峡大坝"},{"type":"paragraph","text":"从容建立在下游的城市哟"},{"type":"paragraph","text":"哦，奉节，我的奉节"},{"type":"paragraph","text":"一座让无形的移民工程"},{"type":"paragraph","text":"坦然建立在心底的城市……"},{"type":"paragraph","text":"一座蕴育当代愚公的城市"},{"type":"paragraph","text":"搬动岁月搬动历史的城市……"},{"type":"paragraph","text":"三峡石"},{"type":"paragraph","text":"你等待了我四亿年（注二）"},{"type":"paragraph","text":"只为目光相遇的一瞬"},{"type":"paragraph","text":"拾起你的时候"},{"type":"paragraph","text":"我拾起了三峡的年轮"},{"type":"paragraph","text":"不，层层叠叠的沉重"},{"type":"paragraph","text":"以及深入骨髓的擦痕"},{"type":"paragraph","text":"都提醒我注意你的身份"},{"type":"paragraph","text":"你是大江之魂！"},{"type":"paragraph","text":"捧住端详聆听"},{"type":"paragraph","text":"江声雨声风声猿声"},{"type":"paragraph","text":"齐齐向这枚三峡石的内心"},{"type":"paragraph","text":"一丝丝地渗透浸润"},{"type":"paragraph","text":"也许你更愿意躺在三峡"},{"type":"paragraph","text":"躺在175米深的水下与鱼儿和水草们聊天"},{"type":"paragraph","text":"和横行的小蟹们嬉戏"},{"type":"paragraph","text":"我把你变成一位“移民”"},{"type":"paragraph","text":"从三峡移向我的书桌只为了听听你的故事"},{"type":"paragraph","text":"屈原、李白、王昭君"},{"type":"paragraph","text":"因为我固执地相信"},{"type":"paragraph","text":"三峡石，你真的见过这些古人……"},{"type":"paragraph","text":"（注一）奉节为川东地下党活动地区，江姐的丈夫牺牲于此。"},{"type":"paragraph","text":"（注二）三峡地壳构造有四亿年历史。"}],"comments":[],"comment_pivots":[],"description":"","page_start":8,"page_end":8}