{"title":"国际军体柔道赛闭幕中国队列奖牌榜第三","authors":["范江怀"],"dates":[{"year":2002,"month":10,"day":21}],"parts":[{"type":"paragraph","text":"国际军体柔道赛闭幕"},{"type":"paragraph","text":"中国队列奖牌榜第三"},{"type":"paragraph","text":"本报北京十月二十日讯国际军事体育理事会第二十八届世界柔道锦标赛今天在这里落幕，中国队以三金二银五铜的成绩列奖牌榜第三位。俄罗斯队以三金五银六铜，排在奖牌榜首位，意大利队以三金四银四铜名列第二。"},{"type":"paragraph","text":"国际军体理事会官方代表米歇尔·圣·博奈上校在闭幕式上称赞本届锦标赛的组织工作完美无缺。本届组委会主任秦怀保少将通过国际军体理事会官方代表，将会旗移交给下届锦标赛承办国意大利的军方代表。"},{"type":"paragraph","text":"（范江怀）"}],"comments":[],"comment_pivots":[],"description":"","page_start":6,"page_end":6}