{"title":"图片","authors":["蒋铎"],"dates":[{"year":2002,"month":10,"day":14}],"parts":[{"type":"paragraph","text":"10月12日，北京市第五中学举行第一届保尔班命名50周年座谈会。"},{"type":"paragraph","text":"师生们从四面八方聚到了北京，当年十四五岁的孩子如今已年过花甲，当时的班主任吴家瑛老师今年已88岁高龄。当年吴老师从微薄的工资中挤出钱来，为同学们买了几本《钢铁是怎样炼成的》，谆谆教诲孩子们像保尔那样做事做人。如今和50年前的学生见面时，她能随口说出学生许多有趣的往事。"},{"type":"paragraph","text":"上图：座谈会上，吴家瑛老师（中）说：“其实，那个时候，我是同你们一起学保尔·柯察金，你们在学，我也在学。保尔是一个品格伟大的人。我们学习他，是为了建设好我们的祖国，是为了人民的幸福。今天我们仍然需要保尔精神。”"},{"type":"paragraph","text":"下图：学生向老师献上鲜花和礼物，表达诚挚的敬意。"},{"type":"paragraph","text":"本报记者蒋铎摄影报道"}],"comments":[],"comment_pivots":[],"description":"","page_start":4,"page_end":4}