{"title":"阿富汗游击队袭击苏联和卡尔迈勒军队","authors":[],"dates":[{"year":1982,"month":10,"day":6}],"parts":[{"type":"paragraph","text":"阿富汗游击队袭击苏联和卡尔迈勒军队"},{"type":"paragraph","text":"新华社伊斯兰堡10月4日电　据阿富汗新闻社今天报道，阿富汗游击队加强了在塔哈尔、巴尔赫、赫拉特和坎大哈省的军事活动，不断袭击苏军和卡尔迈勒政权军队。"},{"type":"paragraph","text":"9月22日晚，阿富汗游击队袭击了坎大哈省斯品布尔达克地区的一个军事哨所，炸毁了这个哨所，整个战斗只用了30分钟。"},{"type":"paragraph","text":"9月23日，在阿富汗第二大城市坎大哈，阿富汗游击队击毁了一辆苏制坦克，打死了这辆坦克上所有人员。"},{"type":"paragraph","text":"在过去的两周里，阿富汗游击队每天在赫拉特进行伏击，造成敌人伤亡。"}],"comments":[],"comment_pivots":[],"description":"","page_start":6,"page_end":6}