{"title":"一颗新星","authors":["臧克家"],"dates":[{"year":1957,"month":10,"day":8}],"parts":[{"type":"paragraph","text":"一颗新星"},{"type":"paragraph","text":"臧克家"},{"type":"paragraph","text":"（一）"},{"type":"paragraph","text":"一颗新星出现在高空，"},{"type":"paragraph","text":"牵动着全世界人类的眼睛，"},{"type":"paragraph","text":"向他拍手吧，向他欢呼吧，"},{"type":"paragraph","text":"他飞，他飞，带着我们兴奋的心。"},{"type":"paragraph","text":"哒哒哒，像亲切的耳语，"},{"type":"paragraph","text":"收音机里发出节奏的声音，"},{"type":"paragraph","text":"一个科学巨人在迈着快步，"},{"type":"paragraph","text":"哒哒地扣着宇宙秘密的大门。"},{"type":"paragraph","text":"（二）"},{"type":"paragraph","text":"一转眼十万八千里，"},{"type":"paragraph","text":"他在九百公里的天上向人类招手："},{"type":"paragraph","text":"飞起来呀，飞起来呀，"},{"type":"paragraph","text":"我们到星际去作逍遥游。"},{"type":"paragraph","text":"路过西半球的时候，"},{"type":"paragraph","text":"他的心特别激动："},{"type":"paragraph","text":"“我是来自苏联的客人呀”，"},{"type":"paragraph","text":"高高地，高高地他掠过了纽约的上空。"}],"comments":[],"comment_pivots":[],"description":"","page_start":8,"page_end":8}