{"title":"玄峻极大使举行酒会和电影招待会  庆祝普天堡战斗胜利三十五周年  韩念龙、王新亭、李强等应邀出席","authors":[],"dates":[{"year":1972,"month":6,"day":3}],"parts":[{"type":"paragraph","text":"玄峻极大使举行酒会和电影招待会"},{"type":"paragraph","text":"庆祝普天堡战斗胜利三十五周年"},{"type":"paragraph","text":"韩念龙、王新亭、李强等应邀出席"},{"type":"paragraph","text":"新华社一九七二年六月二日讯　为庆祝朝鲜人民的伟大领袖金日成同志在抗日战争中领导的普天堡战斗胜利三十五周年，朝鲜民主主义人民共和国驻华大使玄峻极今天下午举行酒会和电影招待会。"},{"type":"paragraph","text":"应邀出席的有，外交部副部长韩念龙，中国人民解放军副总参谋长王新亭，对外贸易部副部长李强以及有关方面负责人张贤约、田维新、赵一萍、申健、张香山、韩宗正、施义之、黄作珍、于步血、宋中、张政德、张子良、曹克强、岳志坚、郭东俊、郑玉珠等。"},{"type":"paragraph","text":"招待会上放映了朝鲜彩色故事影片。"}],"comments":[],"comment_pivots":[],"description":"","page_start":3,"page_end":3}