{"title":"两会口占","authors":["关山月"],"dates":[{"year":1996,"month":3,"day":11}],"parts":[{"type":"paragraph","text":"两会口占"},{"type":"paragraph","text":"七绝二首"},{"type":"paragraph","text":"关山月"},{"type":"paragraph","text":"一"},{"type":"paragraph","text":"九五目标今在望，台阶跨世有蓝图；"},{"type":"paragraph","text":"全民关注议政会，正气新风辟坦途。"},{"type":"paragraph","text":"二"},{"type":"paragraph","text":"两会同声来议政，精神物质论文明；"},{"type":"paragraph","text":"蓝图策划定方向，风顺祥和鼓进程。"},{"type":"paragraph","text":"１９９６年３月４日即兴"}],"comments":[],"comment_pivots":[],"description":"","page_start":2,"page_end":2}