{"title":"表扬","authors":[],"dates":[{"year":1984,"month":9,"day":29}],"parts":[{"type":"paragraph","text":"表扬"},{"type":"paragraph","text":"☆7月26日我接到妹妹从唐山发来的加急电报，写着：26日乘328次列车到京希接。由于没有写明火车到站时间，一时又找不到列车时刻表，我心里很着急。正在这时，电文旁“328次列车十三点零八分到北京站”的附注映入我的眼帘。北新桥邮电局采取的这种便民措施，值得一赞。"},{"type":"paragraph","text":"北京　卢向韬"},{"type":"paragraph","text":"☆我们明久乡乡政府，自筹资金，从6月1日起，选派五名离土不离乡的乡办投递员，办起了乡邮电所。他们把邮件直投到户。现在，我们这里邮信不出屯，收报不出门，当天来的报刊、信件就能与我们见面。"},{"type":"paragraph","text":"黑龙江肇东县　王秀春口述　许有代笔"},{"type":"paragraph","text":"☆九江市人民路粮站，从1964年以来，坚持为老干部和五保户送粮送油上门。为了做到平时店面供应和送粮上门两不误，1978年他们在两个老干部住宿区定点定时供应，每月给点上送粮三次。群众称赞他们是“贴心粮站”、“便民粮站”。"},{"type":"paragraph","text":"江西九江市　单飞　魏朝卿"},{"type":"paragraph","text":"☆8月27日，我乘杭州至衢州的357次列车回金华。这趟车上的列车员服务热情，仅在杭州至金华运行的三个多小时中，列车员为旅客送开水达十一次之多。而且个个态度和蔼可亲，服务热情周到，给乘客留下了深刻的印象。"},{"type":"paragraph","text":"浙江金华　赵宏"},{"type":"paragraph","text":"☆最近看到北京的一些公共汽车，改装了“发光路牌”。这种路牌在夜里清晰可见，能使候车乘客提早辨认是哪路车。这一小小的改革，给夜间乘车的群众带来了方便。"},{"type":"paragraph","text":"北京　王树森"}],"comments":[],"comment_pivots":[],"description":"","page_start":5,"page_end":5}