{"title":"文安建成首座县级综合用塔","authors":["孙万堂"],"dates":[{"year":1987,"month":12,"day":24}],"parts":[{"type":"paragraph","text":"文安建成首座县级综合用塔"},{"type":"paragraph","text":"本报讯　我国第一座县级综合用塔，不久前在河北省文安县建成。"},{"type":"paragraph","text":"这座可供电视差转、调频广播、微波通讯和居民生活用水的综合塔，高75米。其中，水塔高45米，用钢筋混凝土浇铸而成，可容纳200立方水。水塔顶端装有30米高的钢结构接收发射架。"},{"type":"paragraph","text":"这座采用我国先进建筑技术建造的综合塔，具有投资少、造形美观、经久耐用等优点。专家们认为，它具有普遍的推广价值。"},{"type":"paragraph","text":"（孙万堂）"}],"comments":[],"comment_pivots":[],"description":"","page_start":3,"page_end":3}