{"title":"《陈嘉庚先生诞辰１２０周年纪念册》举行首发式","authors":["潘跃"],"dates":[{"year":1995,"month":10,"day":13}],"parts":[{"type":"paragraph","text":"《陈嘉庚先生诞辰１２０周年纪念册》举行首发式"},{"type":"paragraph","text":"本报北京１０月１２日讯记者潘跃报道：《陈嘉庚先生诞辰１２０周年纪念册》今天在人民大会堂举行首发式。"},{"type":"paragraph","text":"纪念册生动地再现了１９９４年纪念陈嘉庚先生诞辰１２０周年活动时的盛况，收集了江泽民、李鹏等党和国家领导人给这位民族伟人的题词。"},{"type":"paragraph","text":"据悉，纪念册在北京举行首发式后，将在香港、澳门、新加坡等地区和国家继续举行赠书仪式，并向世界著名学术团体、各大图书馆赠送，让陈嘉庚精神进一步发扬光大。"},{"type":"paragraph","text":"全国人大常委会副委员长孙起孟，全国政协副主席王兆国、孙孚凌、万国权及彭冲、方毅、杨成武等老同志出席了首发式。"}],"comments":[],"comment_pivots":[],"description":"","page_start":3,"page_end":3}