{"title":"俄任命驻车武装新司令","authors":[],"dates":[{"year":1995,"month":10,"day":14}],"parts":[{"type":"paragraph","text":"俄任命驻车武装新司令"},{"type":"paragraph","text":"新华社莫斯科１０月１２日电据俄通社—塔斯社今天报道，俄罗斯内务部队副总司令什基尔科已被任命为俄驻车臣联合武装力量司令。"},{"type":"paragraph","text":"这家通讯社说，此消息已得到联合武装力量新闻中心的证实。"},{"type":"paragraph","text":"据悉，什基尔科将于近日前往格罗兹尼赴任。他将替代６日在恐怖事件中受重伤的罗曼诺夫将军。"},{"type":"paragraph","text":"现年４７岁的什基尔科中将毕业于总参军事学院，长期在内务部队服役，从１９９３年起担任内务部队副总司令。"}],"comments":[],"comment_pivots":[],"description":"","page_start":3,"page_end":3}