{"title":"国道","authors":["潘涌"],"dates":[{"year":1995,"month":10,"day":2}],"parts":[{"type":"paragraph","text":"国道"},{"type":"paragraph","text":"潘涌"},{"type":"paragraph","text":"以流畅的气韵裁剪岁月"},{"type":"paragraph","text":"以磁性的灵感"},{"type":"paragraph","text":"拼贴希望袅袅的乡镇"},{"type":"paragraph","text":"拥向蓝天抒情的开发区楼群"},{"type":"paragraph","text":"饱孕的芬芳黄金的辉煌"},{"type":"paragraph","text":"随风远播太阳的故乡……"},{"type":"paragraph","text":"十月我们从国道的两岸"},{"type":"paragraph","text":"采撷江南一派成熟的风景"},{"type":"paragraph","text":"深入国道的核心"},{"type":"paragraph","text":"以速度和跨世纪的激情"},{"type":"paragraph","text":"瞬间传动给你奋然的心"},{"type":"paragraph","text":"翩翩欲飞……"}],"comments":[],"comment_pivots":[],"description":"","page_start":4,"page_end":4}