{"title":"武汉研究成功治疗内痔新法","authors":[],"dates":[{"year":1965,"month":1,"day":30}],"parts":[{"type":"paragraph","text":"武汉研究成功治疗内痔新法"},{"type":"paragraph","text":"新华社武汉二十九日电　武汉市中医医院痔瘘科最近研究成一种治疗内痔的新方法——油剂注射液疗法。"},{"type":"paragraph","text":"用来注射的这种油剂是由一些中药和西药配制成的，名叫“内痔枯脱油”。治疗时，只要根据痔核的大小注入适当剂量的注射液，几天以后，痔核就渐渐干枯，自行脱落。"},{"type":"paragraph","text":"由于这种注射液不含有毒成分，对人体没有刺激，注射时不需要麻醉止痛，注射后也没有周身反应。注射后发生的局部肿胀或轻微疼痛，绝大多数病例在几小时以后就可以消失。由于手术操作简便，有些病例可以在门诊施行。"},{"type":"paragraph","text":"使用这种注射枯脱油的治疗方法，经过三百多例临床试验，证明它具有疗效高、疼痛小、适应性广、操作简便和安全经济等优点。"}],"comments":[],"comment_pivots":[],"description":"","page_start":2,"page_end":2}