{"title":"买年画","authors":["陈炳熙"],"dates":[{"year":1961,"month":12,"day":30}],"parts":[{"type":"paragraph","text":"买年画（儿歌）"},{"type":"paragraph","text":"陈炳熙"},{"type":"paragraph","text":"雪不下，风不刮，"},{"type":"paragraph","text":"好天气数着年前二十八。"},{"type":"paragraph","text":"爷爷、奶奶去赶集，"},{"type":"paragraph","text":"年画市上买年画。"},{"type":"paragraph","text":"又有“三英战吕布”，"},{"type":"paragraph","text":"又有“四季如意花”。"},{"type":"paragraph","text":"爷爷、奶奶都不中意，"},{"type":"paragraph","text":"挑来挑去把眼挑花！"},{"type":"paragraph","text":"忽然看见一张画，"},{"type":"paragraph","text":"乐得齐声笑哈哈："},{"type":"paragraph","text":"哪张也没有这张好，"},{"type":"paragraph","text":"——“毛主席来到咱们家”！"}],"comments":[],"comment_pivots":[],"description":"","page_start":6,"page_end":6}