{"title":"亚洲羽毛球锦标赛进入第二阶段比赛  中国队胜新加坡队　中国台北队胜香港队","authors":["谭军","许基仁"],"dates":[{"year":1989,"month":12,"day":21}],"parts":[{"type":"paragraph","text":"亚洲羽毛球锦标赛进入第二阶段比赛"},{"type":"paragraph","text":"中国队胜新加坡队　中国台北队胜香港队"},{"type":"paragraph","text":"新华社上海12月20日电（记者谭军、许基仁）首次来大陆参赛的中国台北羽毛球队今天上午在上海体育馆亮相，第一位出场的张文松苦战3局，以2∶1胜香港名将杨奕琦。"},{"type":"paragraph","text":"亚洲羽毛球锦标赛今天上午和晚上进行了两轮小组循环赛。"},{"type":"paragraph","text":"上午，日本队4∶1胜朝鲜队、印度队5∶0胜斯里兰卡队、中国台北队4∶1胜香港队、泰国队5∶0胜新加坡队。"},{"type":"paragraph","text":"晚上，印度尼西亚、马来西亚、南朝鲜和中国队均以5∶0分别击败了朝鲜、斯里兰卡、香港和新加坡队。"},{"type":"paragraph","text":"中国队今天上场的3名单打选手是：赵剑华、吴文凯和刘军，两对双打选手是：田秉毅和李永波、郑昱闽和黄展忠。"}],"comments":[],"comment_pivots":[],"description":"","page_start":3,"page_end":3}