{"title":"第三十七届世界乒乓球锦标赛  女子单打种子选手分布","authors":[],"dates":[{"year":1983,"month":4,"day":8}],"parts":[{"type":"paragraph","text":"第三十七届世界乒乓球锦标赛"},{"type":"paragraph","text":"女子单打种子选手分布\t1　童玲\t\t（中国）\t8　乌尔班\t（匈牙利）\t9　金京顺\t（朝鲜）\t16　川东加代子\t（日本）\t17　梁英子、\t（南朝鲜）\t24　格雷夫贝格\t（芬兰）\t25　帕拉蒂努什\t（南斯拉夫）\t32　耿丽娟\t（中国）\t33　波波娃\t（苏联）\t40　尹璟美\t（南朝鲜）\t41　萨博\t（匈牙利）\t48　田静\t（中国）\t49　赫拉霍娃\t（捷克斯洛伐克）\t56　神田绘美子\t（日本）\t57　佩尔库钦\t（南斯拉夫）\t64　黄俊群\t（中国）\t65　齐宝香\t（中国）\t72　马戈斯\t（匈牙利）\t73　林德布拉德\t（瑞典）\t80　和田理枝\t（日本）\t81　布拉托娃\t（苏联）\t88　巴蒂尼茨\t（南斯拉夫）\t89　申得花\t（南朝鲜）\t96　戴丽丽\t（中国）\t97　夫里塞科普\t（荷兰）\t104　奥拉\t（匈牙利）\t105　岛内美子\t（日本）\t112　安海淑\t（南朝鲜）\t113　内梅斯\t（罗马尼亚）\t120　科瓦连科\t（苏联）\t121　克鲁格尔\t（西德）\t128　曹燕华\t（中国）"},{"type":"paragraph","text":"中国非种子选手倪夏莲排在第108号。"}],"comments":[],"comment_pivots":[],"description":"","page_start":3,"page_end":3}