{"title":"乌奎高速公路通车","authors":["李忱","王仁倜"],"dates":[{"year":2000,"month":11,"day":4}],"parts":[{"type":"paragraph","text":"乌奎高速公路通车"},{"type":"paragraph","text":"本报记者  李忱  王仁倜"},{"type":"paragraph","text":"11月3日上午，国家重点工程、新疆乌奎高速公路建成通车。"},{"type":"paragraph","text":"乌奎高速公路是国家“五纵七横”国道连云港至霍尔果斯的主干线之一。东起乌鲁木齐市，西至奎屯市，全长265．5公里。工程总投资51．4亿元，其中利用世界银行贷款3亿美元，国家支持12．4亿元，其余部分由自治区自筹。"},{"type":"paragraph","text":"公路于1997年4月开工，面向国内外公开招标。在建设中，新疆采用国际上通行的“菲迪克条款”和世行的要求管理项目，工程质量在1999年全国在建重点公路工程项目“十优”评选中名列第二。"}],"comments":[],"comment_pivots":[],"description":"","page_start":1,"page_end":1}