{"title":"国务院任免一批国家工作人员","authors":[],"dates":[{"year":1985,"month":2,"day":16}],"parts":[{"type":"paragraph","text":"国务院任免一批国家工作人员"},{"type":"paragraph","text":"新华社北京2月15日电  国务院1984年11月2日、1985年1月4日、30日任免一批国家工作人员。"},{"type":"paragraph","text":"任命名单："},{"type":"paragraph","text":"张文寿、张镜源为国务院副秘书长；"},{"type":"paragraph","text":"滕藤、曾宪林、吴明瑜、郭树言为国家科学技术委员会副主任；"},{"type":"paragraph","text":"何济海为商业部副部长；"},{"type":"paragraph","text":"刘复之为中国人民武装警察部队总部第一政治委员，李振军为政治委员，李连秀为司令员，李俊、黄英夫为副司令员，李刚为顾问。"},{"type":"paragraph","text":"免职名单："},{"type":"paragraph","text":"免去陈楚、顾明的国务院副秘书长职务，李觉、周秩、刁筠寿的核工业部顾问职务，李刚的中国人民武装警察部队总部司令员职务。"}],"comments":[],"comment_pivots":[],"description":"","page_start":4,"page_end":4}