{"title":"共产主义者之歌","authors":["季米特尔·舒泰利奇"],"dates":[{"year":1962,"month":11,"day":27}],"parts":[{"type":"paragraph","text":"共产主义者之歌"},{"type":"paragraph","text":"〔阿尔巴尼亚〕季米特尔·舒泰利奇"},{"type":"paragraph","text":"朋友，有这样一个共和国，"},{"type":"paragraph","text":"它很小，但却在建设社会主义；"},{"type":"paragraph","text":"它的敌人是那样强大而又凶恶，"},{"type":"paragraph","text":"但是任何力量也不能摧毁社会主义。"},{"type":"paragraph","text":"这个共和国高举着自由的大旗，"},{"type":"paragraph","text":"矗立在亚得里亚海上；"},{"type":"paragraph","text":"它的敌人是那样强大而又凶恶，蠢蠢欲动，"},{"type":"paragraph","text":"但是大旗依然毫无损伤地在高空飘扬。"},{"type":"paragraph","text":"如果有人问：这个国家"},{"type":"paragraph","text":"怎样制成了这面大旗？"},{"type":"paragraph","text":"有一天，出现了一个新型的党，"},{"type":"paragraph","text":"它把皇帝和暴君的宝座连根拔起。"},{"type":"paragraph","text":"有一天，列宁的祖国，"},{"type":"paragraph","text":"也就是斯大林的祖国，崛然而起；"},{"type":"paragraph","text":"解放的钟声响彻四方，"},{"type":"paragraph","text":"就是在我们的祖国，也听到它的回响。"},{"type":"paragraph","text":"在我们这里出现了一位罕见的勇士，"},{"type":"paragraph","text":"人们对他投出期待的目光；"},{"type":"paragraph","text":"他领导着党，高举着大旗，"},{"type":"paragraph","text":"他把大旗插在坚固的岩石上。"},{"type":"paragraph","text":"敌人是那样强大而又凶恶，愤怒得发狂，"},{"type":"paragraph","text":"他们妄想降下这面骄傲的大旗；"},{"type":"paragraph","text":"但是勇士粉碎了敌人，"},{"type":"paragraph","text":"从此任何人再也不敢玷污这面大旗。"},{"type":"paragraph","text":"时间迅速飞逝过去，"},{"type":"paragraph","text":"可是这面大旗仍然在高空飘扬，"},{"type":"paragraph","text":"就这样，要世世代代地相传下去，"},{"type":"paragraph","text":"从一只手上传到另一只手上。"},{"type":"paragraph","text":"朋友，有这样一个共和国，"},{"type":"paragraph","text":"它很小，但却在建设社会主义；"},{"type":"paragraph","text":"尽管敌人愤怒得发狂，"},{"type":"paragraph","text":"但是他还要建设共产主义，使祖国变得更加富强。"},{"type":"paragraph","text":"（李宁来译　戈宝权校）"}],"comments":[],"comment_pivots":[],"description":"","page_start":6,"page_end":6}