{"title":"金牌榜","authors":[],"dates":[{"year":1998,"month":12,"day":15}],"parts":[{"type":"paragraph","text":"金牌榜"},{"type":"paragraph","text":"（截至12月14日）"},{"type":"paragraph","text":"国家和地区\t       金牌\t银牌\t铜牌\t总计"},{"type":"paragraph","text":"中国\t\t84\t58\t41\t183"},{"type":"paragraph","text":"韩国\t\t42\t25\t34\t101"},{"type":"paragraph","text":"日本\t\t35\t37\t46\t118"},{"type":"paragraph","text":"哈萨克斯坦\t        14\t18\t21\t53"},{"type":"paragraph","text":"中国台北\t        14\t10\t22\t46"},{"type":"paragraph","text":"泰国\t\t13\t17\t24\t54"},{"type":"paragraph","text":"朝鲜\t\t5\t1\t16\t22"}],"comments":[],"comment_pivots":[],"description":"","page_start":8,"page_end":8}